dbus_notifier/__init__.py
dbus_notifier/notifysender.py
dbus_notifier/icons/feather_on_grey.png
dbus_notifier-1.1.1.data/data/.env_dbus_notifier
dbus_notifier-1.1.1.data/data/dbus_notifier/icons/feather_on_grey.png
dbus_notifier-1.1.1.dist-info/licenses/LICENSE
dbus_notifier-1.1.1.dist-info/METADATA
dbus_notifier-1.1.1.dist-info/WHEEL
dbus_notifier-1.1.1.dist-info/top_level.txt
dbus_notifier-1.1.1.dist-info/RECORD
