Metadata-Version: 2.4
Name: dbus-notifier
Version: 1.1.1
Summary: A small dbus notifier package
Author: Adam Bukolt
Author-email: Adam Bukolt <abukolt@gmx.com>
Project-URL: Homepage, https://github.com/adambmarsh/dbusnotify
Classifier: Programming Language :: Python :: 3
Classifier: License :: OSI Approved :: MIT License
Classifier: Operating System :: OS Independent
Requires-Python: >=3.10
License-File: LICENSE
Requires-Dist: dbus-python>=1.4.0
Requires-Dist: dbusnotify>=0.0.2
Requires-Dist: dotenv>=0.9.9
Requires-Dist: python-dotenv>=1.1.1
Requires-Dist: setuptools>=80.9.0
Dynamic: author
Dynamic: license-file
Dynamic: requires-python
